{
  "//": "Este es el catálogo central de imágenes. Para cambiar la imagen de un curso, simplemente reemplaza la URL correspondiente aquí.",
  "course-web-react": "https://picsum.photos/seed/react/600/400",
  "course-web-vue": "https://picsum.photos/seed/vue/600/400",
  "course-ia-python": "https://picsum.photos/seed/python/600/400",
  "course-ia-ml": "https://picsum.photos/seed/ml/600/400",
  "course-ux-investigacion": "https://picsum.photos/seed/ux/600/400",
  "course-cloud-aws": "https://picsum.photos/seed/aws/600/400",
  "course-rh-tech": "https://picsum.photos/seed/hr/600/400",
  "course-negocios-finanzas": "https://picsum.photos/seed/business/600/400",
  "course-english-business": "https://picsum.photos/seed/english/600/400",
  "course-cyber-intro": "https://picsum.photos/seed/cyber/600/400",
  "course-movil-flutter": "https://picsum.photos/seed/flutter/600/400",
  "course-web3-solidity": "https://picsum.photos/seed/solidity/600/400",
  "course-fin-personal": "https://picsum.photos/seed/finance/600/400",
  "course-dg-branding": "https://picsum.photos/seed/branding/600/400",
  "course-mkt-seo": "https://picsum.photos/seed/seo/600/400",
  "course-soft-comunicacion": "https://picsum.photos/seed/softskills/600/400",
  "course-av-edicion": "https://picsum.photos/seed/videoedit/600/400",
  "course-prog-python": "https://picsum.photos/seed/progpython/600/400",
  "course-startup-mvp": "https://picsum.photos/seed/mvp/600/400",
  "course-prog-javascript": "https://picsum.photos/seed/progjs/600/400",
  "course-prog-java": "https://picsum.photos/seed/progjava/600/400",
  "course-prog-cpp": "https://picsum.photos/seed/progcpp/600/400",
  "course-web-node": "https://picsum.photos/seed/node/600/400",
  "course-web-typescript": "https://picsum.photos/seed/typescript/600/400",
  "course-web-php": "https://picsum.photos/seed/php/600/400",
  "course-ia-datascience-python": "https://picsum.photos/seed/datascience/600/400",
  "course-ia-r": "https://picsum.photos/seed/rlang/600/400",
  "course-ia-sql": "https://picsum.photos/seed/sql/600/400",
  "course-ux-figma": "https://picsum.photos/seed/figma/600/400",
  "course-cloud-docker": "https://picsum.photos/seed/docker/600/400",
  "course-movil-swift": "https://picsum.photos/seed/swift/600/400",
  "course-movil-kotlin": "https://picsum.photos/seed/kotlin/600/400",
  "course-movil-dart": "https://picsum.photos/seed/dart/600/400",
  "course-web3-rust": "https://picsum.photos/seed/rust/600/400",
  "course-rh-reclutamiento": "https://picsum.photos/seed/recruitment/600/400",
  "course-rh-cultura": "https://picsum.photos/seed/culture/600/400",
  "course-negocios-estrategia": "https://picsum.photos/seed/strategy/600/400",
  "course-english-entrevistas": "https://picsum.photos/seed/interview/600/400",
  "course-english-comunicacion": "https://picsum.photos/seed/communication/600/400",
  "hero-image": "https://picsum.photos/seed/hero-learning/600/400",
  "lesson-default": "https://picsum.photos/seed/lesson-placeholder/600/400",
  "prog-python-comp": "https://picsum.photos/seed/python-comp/600/400",
  "prog-python-pip": "https://picsum.photos/seed/python-pip/600/400",
  "prog-js-closures": "https://picsum.photos/seed/js-closures/600/400",
  "finanzas-emprendedores": "https://picsum.photos/seed/finance-entrepreneur/600/400",
  "analisis-financiero-excel": "https://picsum.photos/seed/excel-finance/600/400",
  "estrategia-negocios-digitales": "https://picsum.photos/seed/digital-business/600/400",
  "metricas-negocio": "https://picsum.photos/seed/business-metrics/600/400",
  "english-negocios": "https://picsum.photos/seed/english-for-business/600/400",
  "rh-reclutamiento-tech": "https://picsum.photos/seed/tech-recruiting/600/400",
  "rh-cultura-org": "https://picsum.photos/seed/organization-culture/600/400",
  "fund-arq-software": "https://picsum.photos/seed/software-architecture/600/400",
  "prof-arq-software": "https://picsum.photos/seed/pro-architecture/600/400",
  "arq-limpias-dev": "https://picsum.photos/seed/clean-architecture/600/400",
  "pract-arq-backend": "https://picsum.photos/seed/backend-architecture/600/400",
  "audio-alta-concurrencia": "https://picsum.photos/seed/concurrency/600/400",
  "audio-arq-frontend": "https://picsum.photos/seed/frontend-architecture/600/400",
  "arq-css": "https://picsum.photos/seed/css-architecture/600/400",
  "ssr-react": "https://picsum.photos/seed/ssr-react/600/400",
  "nextjs-jamstack": "https://picsum.photos/seed/nextjs-jamstack/600/400",
  "intro-jamstack": "https://picsum.photos/seed/intro-jamstack/600/400",
  "ssr-nuxt2": "https://picsum.photos/seed/ssr-nuxt/600/400",
  "web-astro": "https://picsum.photos/seed/astro-web/600/400",
  "angular-avanzado": "https://picsum.photos/seed/advanced-angular/600/400",
  "nextjs-avanzado": "https://picsum.photos/seed/advanced-nextjs/600/400",
  "nodejs-auth-microservices": "https://picsum.photos/seed/node-microservices/600/400",
  "go-eventos-cqrs": "https://picsum.photos/seed/go-cqrs/600/400",
  "go-grpc": "https://picsum.photos/seed/go-grpc/600/400",
  "graphql-nodejs": "https://picsum.photos/seed/graphql-node/600/400",
  "avanzado-nodejs-graphql": "https://picsum.photos/seed/advanced-graphql/600/400",
  "fund-observabilidad-new-relic": "https://picsum.photos/seed/new-relic-obs/600/400",
  "ing-observabilidad-new-relic": "https://picsum.photos/seed/new-relic-eng/600/400",
  "obs-agentes-ai-langsmith": "https://picsum.photos/seed/langsmith-ai/600/400",
  "monorepos-nx": "https://picsum.photos/seed/nx-monorepo/600/400",
  "fund-db": "https://picsum.photos/seed/database-fundamentals/600/400",
  "sql-mysql": "https://picsum.photos/seed/sql-mysql/600/400",
  "postgresql": "https://picsum.photos/seed/postgresql/600/400",
  "db-mysql-mariadb": "https://picsum.photos/seed/mariadb/600/400",
  "opt-db-sql-server": "https://picsum.photos/seed/sql-server/600/400",
  "db-nosql": "https://picsum.photos/seed/nosql-db/600/400",
  "intro-mongodb": "https://picsum.photos/seed/mongodb-intro/600/400",
  "modelado-mongodb": "https://picsum.photos/seed/mongodb-modeling/600/400",
  "mongodb-aggregation": "https://picsum.photos/seed/mongodb-aggregation/600/400",
  "intro-elasticsearch": "https://picsum.photos/seed/elasticsearch/600/400",
  "azure-cache-redis": "https://picsum.photos/seed/azure-redis/600/400",
  "intro-desarrollo-backend": "https://picsum.photos/seed/backend-intro/600/400",
  "java-basico": "https://picsum.photos/seed/java-basics/600/400",
  "java-se-sql": "https://picsum.photos/seed/java-sql/600/400",
  "java-spring-boot": "https://picsum.photos/seed/spring-boot/600/400",
  "java-spring": "https://picsum.photos/seed/java-spring/600/400",
  "java-spring-data-jpa": "https://picsum.photos/seed/spring-jpa/600/400",
  "java-spring-security": "https://picsum.photos/seed/spring-security/600/400",
  "fund-nodejs": "https://picsum.photos/seed/nodejs-fundamentals/600/400",
  "backend-expressjs": "https://picsum.photos/seed/expressjs/600/400",
  "api-first": "https://picsum.photos/seed/api-first/600/400",
  "backend-nestjs": "https://picsum.photos/seed/nestjs/600/400",
  "nestjs-modular": "https://picsum.photos/seed/nestjs-modular/600/400",
  "nestjs-mongodb": "https://picsum.photos/seed/nestjs-mongo/600/400",
  "nestjs-typeorm": "https://picsum.photos/seed/nestjs-typeorm/600/400",
  "nestjs-auth": "https://picsum.photos/seed/nestjs-auth/600/400",
  "backend-nodejs-postgres": "https://picsum.photos/seed/node-postgres/600/400",
  "backend-nodejs-auth": "https://picsum.photos/seed/node-auth/600/400",
  "api-rest-js-fund": "https://picsum.photos/seed/rest-api-js/600/400",
  "api-rest-js-real": "https://picsum.photos/seed/real-world-api/600/400",
  "api-rest-js-perf": "https://picsum.photos/seed/api-performance/600/400",
  "real-time-socketio": "https://picsum.photos/seed/socketio/600/400",
  "nodejs-avanzado-2023": "https://picsum.photos/seed/advanced-node-2023/600/400",
  "cert-nodejs-openjs-2023": "https://picsum.photos/seed/openjs-cert/600/400",
  "webpack-express-react-ts": "https://picsum.photos/seed/webpack-react/600/400",
  "firebase-angular-20": "https://picsum.photos/seed/firebase-angular/600/400",
  "php-avanzado": "https://picsum.photos/seed/advanced-php/600/400",
  "fund-php": "https://picsum.photos/seed/php-fundamentals/600/400",
  "php-html": "https://picsum.photos/seed/php-with-html/600/400",
  "php-cookies-sesiones": "https://picsum.photos/seed/php-sessions/600/400",
  "php-db": "https://picsum.photos/seed/php-database/600/400",
  "api-rest-php": "https://picsum.photos/seed/php-rest-api/600/400",
  "intro-frameworks-php": "https://picsum.photos/seed/php-frameworks/600/400",
  "laravel-basico": "https://picsum.photos/seed/laravel-basics/600/400",
  "intro-laravel-9": "https://picsum.photos/seed/laravel-9/600/400",
  "api-rest-laravel": "https://picsum.photos/seed/laravel-api/600/400",
  "api-rest-laravel-buenas-practicas": "https://picsum.photos/seed/laravel-best-practices/600/400",
  "laravel-livewire": "https://picsum.photos/seed/laravel-livewire/600/400",
  "intro-laravel-8": "https://picsum.photos/seed/laravel-8/600/400",
  "laravel-tdd": "https://picsum.photos/seed/laravel-tdd/600/400",
  "practico-symfony": "https://picsum.photos/seed/symfony-practice/600/400",
  "symfony-framework": "https://picsum.photos/seed/symfony/600/400",
  "fastapi-curso": "https://picsum.photos/seed/fastapi/600/400",
  "flask-curso": "https://picsum.photos/seed/flask/600/400",
  "django-curso": "https://picsum.photos/seed/django/600/400",
  "django-rest-framework": "https://picsum.photos/seed/django-rest/600/400",
  "deploy-python-nube": "https://picsum.photos/seed/python-deploy/600/400",
  "intro-ruby-on-rails": "https://picsum.photos/seed/ruby-on-rails/600/400",
  "api-ruby-on-rails": "https://picsum.photos/seed/rails-api/600/400",
  "intermedio-ruby-on-rails": "https://picsum.photos/seed/intermediate-rails/600/400",
  "angular-componentes-servicios": "https://picsum.photos/seed/angular-components/600/400",
  "angular-forms": "https://picsum.photos/seed/angular-forms/600/400",
  "consumo-apis-rest-angular": "https://picsum.photos/seed/angular-api/600/400",
  "angular-router": "https://picsum.photos/seed/angular-router/600/400",
  "auth-angular": "https://picsum.photos/seed/angular-auth/600/400",
  "maquetacion-angular-cdk-tailwind": "https://picsum.photos/seed/angular-tailwind/600/400",
  "practico-angular-trello": "https://picsum.photos/seed/angular-trello/600/400",
  "angular-creacion-apps-web": "https://picsum.photos/seed/angular-apps/600/400",
  "js-dom": "https://picsum.photos/seed/javascript-dom/600/400",
  "ecmascript-historia": "https://picsum.photos/seed/ecmascript/600/400",
  "npm-gestion-paquetes": "https://picsum.photos/seed/npm/600/400",
  "intro-empaquetadores-web": "https://picsum.photos/seed/webpack-intro/600/400",
  "webpack-curso": "https://picsum.photos/seed/webpack-course/600/400",
  "js-web-components": "https://picsum.photos/seed/web-components/600/400",
  "spa-js-vanilla": "https://picsum.photos/seed/vanillajs-spa/600/400",
  "debugging-chrome-devtools": "https://picsum.photos/seed/devtools/600/400",
  "optimizacion-web": "https://picsum.photos/seed/web-optimization/600/400",
  "vitejs-curso": "https://picsum.photos/seed/vitejs/600/400",
  "solidjs-curso": "https://picsum.photos/seed/solidjs/600/400",
  "svelte-curso": "https://picsum.photos/seed/svelte/600/400",
  "react-js-curso": "https://picsum.photos/seed/react-course/600/400",
  "react-manejo-estado": "https://picsum.photos/seed/react-state/600/400",
  "react-patrones-render": "https://picsum.photos/seed/react-patterns/600/400",
  "react-router-curso": "https://picsum.photos/seed/react-router/600/400",
  "profesional-react-redux": "https://picsum.photos/seed/react-redux/600/400",
  "react-avanzado": "https://picsum.photos/seed/advanced-react/600/400",
  "react-typescript": "https://picsum.photos/seed/react-ts/600/400",
  "vue-intro-fundamentos": "https://picsum.photos/seed/vue-fundamentals/600/400",
  "vue-componentes-composition": "https://picsum.photos/seed/vue-composition/600/400",
  "vue-reactividad-3": "https://picsum.photos/seed/vue-reactivity/600/400",
  "practico-vue": "https://picsum.photos/seed/vue-practice/600/400",
  "vue-router-curso-2": "https://picsum.photos/seed/vue-router/600/400",
  "vue-vuex": "https://picsum.photos/seed/vuex/600/400",
  "vue-pinia": "https://picsum.photos/seed/vue-pinia/600/400",
  "basico-vue2": "https://picsum.photos/seed/vue2-basics/600/400",
  "avanzado-vue2": "https://picsum.photos/seed/vue2-advanced/600/400",
  "testing-vue2": "https://picsum.photos/seed/vue2-testing/600/400",
  "unit-testing-vue3": "https://picsum.photos/seed/vue3-testing/600/400",
  "frontend-developer-curso": "https://picsum.photos/seed/frontend-dev/600/400",
  "practico-frontend-developer": "https://picsum.photos/seed/frontend-practice/600/400",
  "css-curso": "https://picsum.photos/seed/css-course/600/400",
  "responsive-design-mobile-first": "https://picsum.photos/seed/responsive-design/600/400",
  "practico-maquetacion-css": "https://picsum.photos/seed/css-layout-practice/600/400",
  "diseno-web-css-grid-flexbox": "https://picsum.photos/seed/css-grid-flexbox/600/400",
  "css-grid-basico": "https://picsum.photos/seed/css-grid-basics/600/400",
  "profesional-css-grid-layout": "https://picsum.photos/seed/pro-css-grid/600/400",
  "transformaciones-transiciones-css": "https://picsum.photos/seed/css-transforms/600/400",
  "animaciones-css": "https://picsum.photos/seed/css-animations/600/400",
  "fundamentos-sass": "https://picsum.photos/seed/sass-fundamentals/600/400",
  "tailwindcss-curso": "https://picsum.photos/seed/tailwindcss/600/400",
  "practico-maquetacion-animaciones-css": "https://picsum.photos/seed/css-animation-layout/600/400",
  "materialize-curso": "https://picsum.photos/seed/materialize-css/600/400",
  "intro-web-historia": "https://picsum.photos/seed/web-history/600/400",
  "basico-computadores-informatica": "https://picsum.photos/seed/computer-basics/600/400",
  "intro-terminal": "https://picsum.photos/seed/terminal-intro/600/400",
  "fund-ingenieria-software": "https://picsum.photos/seed/software-eng-fund/600/400",
  "html-curso": "https://picsum.photos/seed/html-course/600/400",
  "practico-html-css": "https://picsum.photos/seed/html-css-practice/600/400",
  "gratis-programacion-basica": "https://picsum.photos/seed/basic-programming/600/400",
  "git-github-curso": "https://picsum.photos/seed/git-github/600/400",
  "fund-criptografia": "https://picsum.photos/seed/cryptography/600/400",
  "owasp-top-10": "https://picsum.photos/seed/owasp-top-10/600/400",
  "ciberseguridad-desarrollo-web": "https://picsum.photos/seed/web-cybersecurity/600/400",
  "oauth-openid": "https://picsum.photos/seed/oauth-oidc/600/400",
  "auth0-implementacion": "https://picsum.photos/seed/auth0/600/400",
  "secretos-js-proteccion": "https://picsum.photos/seed/js-secrets/600/400",
  "nextjs-seguridad-owasp": "https://picsum.photos/seed/nextjs-security/600/400",
  "nextjs-auth-curso": "https://picsum.photos/seed/nextjs-auth/600/400",
  "fund-pruebas-software": "https://picsum.photos/seed/software-testing/600/400",
  "intro-automatizacion-pruebas": "https://picsum.photos/seed/test-automation/600/400",
  "intro-testing-js": "https://picsum.photos/seed/js-testing/600/400",
  "react-testing-library": "https://picsum.photos/seed/react-testing-lib/600/400",
  "angular-unit-testing-servicios": "https://picsum.photos/seed/angular-test-services/600/400",
  "angular-unit-testing-componentes": "https://picsum.photos/seed/angular-test-components/600/400",
  "angular-unit-testing-formularios": "https://picsum.photos/seed/angular-test-forms/600/400",
  "angular-unit-testing-rutas": "https://picsum.photos/seed/angular-test-routes/600/400",
  "pruebas-unitarias-angular": "https://picsum.photos/seed/angular-unit-tests/600/400",
  "automatizacion-cypress": "https://picsum.photos/seed/cypress-automation/600/400",
  "automatizacion-backend-cypress": "https://picsum.photos/seed/cypress-backend/600/400",
  "cypress-avanzado": "https://picsum.photos/seed/advanced-cypress/600/400",
  "automatizacion-puppeteer": "https://picsum.photos/seed/puppeteer/600/400",
  "avanzado-puppeteer": "https://picsum.photos/seed/advanced-puppeteer/600/400",
  "automatizacion-playwright": "https://picsum.photos/seed/playwright/600/400",
  "e2e-testing-api-rest-nodejs": "https://picsum.photos/seed/e2e-testing-node/600/400",
  "performance-testing-nodejs-k6": "https://picsum.photos/seed/k6-performance/600/400",
  "basico-testing-php-laravel": "https://picsum.photos/seed/laravel-testing-basics/600/400",
  "basico-testing-java": "https://picsum.photos/seed/java-testing-basics/600/400",
  "unit-testing-csharp-dotnet": "https://picsum.photos/seed/dotnet-testing/600/400",
  "unit-testing-go": "https://picsum.photos/seed/go-testing/600/400",
  "unit-testing-python": "https://picsum.photos/seed/python-testing/600/400",
  "intro-devops": "https://picsum.photos/seed/intro-devops/600/400",
  "profesional-devops": "https://picsum.photos/seed/pro-devops/600/400",
  "docker-fundamentos": "https://picsum.photos/seed/docker-fundamentals/600/400",
  "docker-avanzado": "https://picsum.photos/seed/advanced-docker/600/400",
  "swarm-curso": "https://picsum.photos/seed/docker-swarm/600/400",
  "kubernetes-curso": "https://picsum.photos/seed/kubernetes/600/400",
  "terraform-curso": "https://picsum.photos/seed/terraform/600/400",
  "iac-aws": "https://picsum.photos/seed/iac-aws/600/400",
  "github-actions-curso": "https://picsum.photos/seed/github-actions/600/400",
  "azure-devops-ci-cd": "https://picsum.photos/seed/azure-devops/600/400",
  "intro-deploy-apps": "https://picsum.photos/seed/app-deployment/600/400",
  "serverless-framework-aws": "https://picsum.photos/seed/serverless-aws/600/400",
  "avanzado-serverless-aws": "https://picsum.photos/seed/advanced-serverless/600/400",
  "aws-cloud-practitioner": "https://picsum.photos/seed/aws-practitioner/600/400",
  "intro-gcp": "https://picsum.photos/seed/gcp-intro/600/400",
  "fund-azure-az900": "https://picsum.photos/seed/azure-az900/600/400"
}
